pyangbind/__init__.py
pyangbind/helpers/__init__.py
pyangbind/helpers/identity.py
pyangbind/helpers/misc.py
pyangbind/lib/__init__.py
pyangbind/lib/base.py
pyangbind/lib/pybindJSON.py
pyangbind/lib/serialise.py
pyangbind/lib/xpathhelper.py
pyangbind/lib/yangtypes.py
pyangbind/plugin/__init__.py
pyangbind/plugin/pybind.py
pyangbind-0.8.5.dist-info/LICENSE
pyangbind-0.8.5.dist-info/METADATA
pyangbind-0.8.5.dist-info/WHEEL
pyangbind-0.8.5.dist-info/top_level.txt
pyangbind-0.8.5.dist-info/RECORD
