Metadata-Version: 2.1
Name: pyangbind
Version: 0.8.5
Summary: PyangBind is a plugin for pyang which converts YANG data models into a Python class hierarchy, such that Python can be used to manipulate data that conforms with a YANG model.
Home-page: https://github.com/robshakir/pyangbind
Author: Rob Shakir
Author-email: rjs@rob.sh
License: Apache License, Version 2.0
Keywords: yang,pyang
Classifier: Development Status :: 4 - Beta
Classifier: Intended Audience :: Telecommunications Industry
Classifier: Intended Audience :: Developers
Classifier: Topic :: Software Development :: Code Generators
Classifier: License :: OSI Approved :: Apache Software License
Classifier: Programming Language :: Python :: 3.7
Classifier: Programming Language :: Python :: 3.8
Classifier: Programming Language :: Python :: 3.9
Classifier: Programming Language :: Python :: 3.10
Classifier: Programming Language :: Python :: 3.11
Classifier: Programming Language :: Python :: Implementation :: CPython
Classifier: Programming Language :: Python :: Implementation :: PyPy
Requires-Python: >=3.7
License-File: LICENSE
Requires-Dist: pyang
Requires-Dist: lxml
Requires-Dist: regex
Requires-Dist: six
Requires-Dist: enum34
